[{"userid": 7625701, "user": "Crashingthewaves", "pageid": 18791173, "revid": 230990218, "parentid": 230989044, "ns": 1, "title": "Talk:2008 Beijing Drum Tower stabbings", "timestamp": "2008-08-10T10:00:57Z", "comment": "/* Notable */", "size": 2294, "sizediff": 863}, {"userid": 7625701, "user": "Crashingthewaves", "pageid": 21716463, "revid": 230994628, "parentid": 230993700, "ns": 0, "title": "2008 Beijing Drum Tower stabbings", "timestamp": "2008-08-10T10:42:51Z", "comment": "", "size": 2544, "sizediff": 11}, {"userid": 7625701, "user": "Crashingthewaves", "pageid": 18791258, "revid": 230996015, "parentid": 230990315, "ns": 4, "title": "Wikipedia:Articles for deletion/2008 Beijing Drum Tower stabbings", "timestamp": "2008-08-10T10:54:54Z", "comment": "/* 2008 Olympics attack on American nationals */", "size": 8756, "sizediff": 665}, {"userid": 7625701, "user": "Crashingthewaves", "pageid": 18791258, "revid": 230996448, "parentid": 230996311, "ns": 4, "title": "Wikipedia:Articles for deletion/2008 Beijing Drum Tower stabbings", "timestamp": "2008-08-10T10:59:13Z", "comment": "/* 2008 Olympics attack on American nationals */", "size": 9523, "sizediff": 80}, {"userid": 7625701, "user": "Crashingthewaves", "pageid": 18798063, "revid": 231424501, "parentid": 231407008, "ns": 4, "title": "Wikipedia:Articles for deletion/2008 Olympics attack on American nationals (2nd nomination)", "timestamp": "2008-08-12T10:26:34Z", "comment": "/* 2008 Olympics attack on American nationals */", "size": 32261, "sizediff": 495}, {"userid": 7625701, "user": "Crashingthewaves", "pageid": 18798063, "revid": 231425169, "parentid": 231424501, "ns": 4, "title": "Wikipedia:Articles for deletion/2008 Olympics attack on American nationals (2nd nomination)", "timestamp": "2008-08-12T10:33:13Z", "comment": "", "size": 32240, "sizediff": -21}, {"userid": 7625701, "user": "Crashingthewaves", "pageid": 18798063, "revid": 231427306, "parentid": 231425169, "ns": 4, "title": "Wikipedia:Articles for deletion/2008 Olympics attack on American nationals (2nd nomination)", "timestamp": "2008-08-12T10:51:10Z", "comment": "", "size": 33454, "sizediff": 1214}, {"userid": 7625701, "user": "Crashingthewaves", "pageid": 18798063, "revid": 231673483, "parentid": 231664631, "ns": 4, "title": "Wikipedia:Articles for deletion/2008 Olympics attack on American nationals (2nd nomination)", "timestamp": "2008-08-13T12:58:38Z", "comment": "/* 2008 Olympics attack on American nationals */", "size": 41713, "sizediff": 1200}, {"userid": 7625701, "user": "Crashingthewaves", "pageid": 18798063, "revid": 231673547, "parentid": 231673483, "ns": 4, "title": "Wikipedia:Articles for deletion/2008 Olympics attack on American nationals (2nd nomination)", "timestamp": "2008-08-13T12:59:12Z", "comment": "/* 2008 Olympics attack on American nationals */", "size": 41822, "sizediff": 109}, {"userid": 7625701, "user": "Crashingthewaves", "pageid": 18798063, "revid": 231673801, "parentid": 231673547, "ns": 4, "title": "Wikipedia:Articles for deletion/2008 Olympics attack on American nationals (2nd nomination)", "timestamp": "2008-08-13T13:00:52Z", "comment": "/* 2008 Olympics attack on American nationals */", "size": 41836, "sizediff": 14}, {"userid": 7625701, "user": "Crashingthewaves", "pageid": 18798063, "revid": 231674485, "parentid": 231673801, "ns": 4, "title": "Wikipedia:Articles for deletion/2008 Olympics attack on American nationals (2nd nomination)", "timestamp": "2008-08-13T13:05:35Z", "comment": "/* 2008 Olympics attack on American nationals */", "size": 42096, "sizediff": 260}, {"userid": 7625701, "user": "Crashingthewaves", "pageid": 18798063, "revid": 231675401, "parentid": 231674692, "ns": 4, "title": "Wikipedia:Articles for deletion/2008 Olympics attack on American nationals (2nd nomination)", "timestamp": "2008-08-13T13:12:06Z", "comment": "/* 2008 Olympics attack on American nationals */", "size": 42894, "sizediff": 263}, {"userid": 7625701, "user": "Crashingthewaves", "pageid": 18798063, "revid": 231675705, "parentid": 231675401, "ns": 4, "title": "Wikipedia:Articles for deletion/2008 Olympics attack on American nationals (2nd nomination)", "timestamp": "2008-08-13T13:14:21Z", "comment": "/* 2008 Olympics attack on American nationals */", "size": 43313, "sizediff": 419}, {"userid": 7625701, "user": "Crashingthewaves", "pageid": 18798063, "revid": 231677314, "parentid": 231676638, "ns": 4, "title": "Wikipedia:Articles for deletion/2008 Olympics attack on American nationals (2nd nomination)", "timestamp": "2008-08-13T13:24:58Z", "comment": "/* 2008 Olympics attack on American nationals */", "size": 44471, "sizediff": 499}, {"userid": 7625701, "user": "Crashingthewaves", "pageid": 2156480, "revid": 231680009, "parentid": 231674863, "ns": 3, "title": "User talk:The Rambling Man", "timestamp": "2008-08-13T13:42:02Z", "comment": "", "size": 36794, "sizediff": 164}, {"userid": 7625701, "user": "Crashingthewaves", "pageid": 2156480, "revid": 231680084, "parentid": 231680009, "ns": 3, "title": "User talk:The Rambling Man", "timestamp": "2008-08-13T13:42:32Z", "comment": "/* Lewis Young */", "size": 36795, "sizediff": 1}, {"userid": 7625701, "user": "Crashingthewaves", "pageid": 2600803, "revid": 231680620, "parentid": 231536894, "ns": 3, "title": "User talk:Elliskev", "timestamp": "2008-08-13T13:46:25Z", "comment": "/* Well */ new section", "size": 9508, "sizediff": 423}, {"userid": 7625701, "user": "Crashingthewaves", "pageid": 2156480, "revid": 231681280, "parentid": 231680695, "ns": 3, "title": "User talk:The Rambling Man", "timestamp": "2008-08-13T13:50:35Z", "comment": "/* Look */ new section", "size": 37009, "sizediff": 379}, {"userid": 7625701, "user": "Crashingthewaves", "pageid": 18798272, "revid": 231681398, "parentid": 231681099, "ns": 3, "title": "User talk:Crashingthewaves", "timestamp": "2008-08-13T13:51:14Z", "comment": "/* Break */", "size": 583, "sizediff": -607}, {"userid": 7625701, "user": "Crashingthewaves", "pageid": 2600803, "revid": 231681594, "parentid": 231680620, "ns": 3, "title": "User talk:Elliskev", "timestamp": "2008-08-13T13:52:26Z", "comment": "/* Well */", "size": 9665, "sizediff": 157}, {"userid": 7625701, "user": "Crashingthewaves", "pageid": 2156480, "revid": 231682228, "parentid": 231681992, "ns": 3, "title": "User talk:The Rambling Man", "timestamp": "2008-08-13T13:56:05Z", "comment": "", "size": 36949, "sizediff": 319}, {"userid": 7625701, "user": "Crashingthewaves", "pageid": 27227370, "revid": 231682941, "parentid": 231682270, "ns": 3, "title": "User talk:Cobaltbluetony", "timestamp": "2008-08-13T14:00:25Z", "comment": "", "size": 21185, "sizediff": 338}, {"userid": 7625701, "user": "Crashingthewaves", "pageid": 18798272, "revid": 231683063, "parentid": 231682786, "ns": 3, "title": "User talk:Crashingthewaves", "timestamp": "2008-08-13T14:01:04Z", "comment": "/* Break */", "size": 1232, "sizediff": -1259}, {"userid": 7625701, "user": "Crashingthewaves", "pageid": 2156480, "revid": 231683326, "parentid": 231682539, "ns": 3, "title": "User talk:The Rambling Man", "timestamp": "2008-08-13T14:02:37Z", "comment": "", "size": 36871, "sizediff": 241}, {"userid": 7625701, "user": "Crashingthewaves", "pageid": 2156480, "revid": 231684011, "parentid": 231683462, "ns": 3, "title": "User talk:The Rambling Man", "timestamp": "2008-08-13T14:06:47Z", "comment": "", "size": 36741, "sizediff": 111}, {"userid": 7625701, "user": "Crashingthewaves", "pageid": 18798272, "revid": 231684360, "parentid": 231684223, "ns": 3, "title": "User talk:Crashingthewaves", "timestamp": "2008-08-13T14:08:57Z", "comment": "/* 2008 Olympics attack on American nationals (2nd nomination) */", "size": 931, "sizediff": -931}, {"userid": 7625701, "user": "Crashingthewaves", "pageid": 2156480, "revid": 231684590, "parentid": 231684091, "ns": 3, "title": "User talk:The Rambling Man", "timestamp": "2008-08-13T14:10:15Z", "comment": "", "size": 36898, "sizediff": 268}, {"userid": 7625701, "user": "Crashingthewaves", "pageid": 18798272, "revid": 231685451, "parentid": 231685364, "ns": 3, "title": "User talk:Crashingthewaves", "timestamp": "2008-08-13T14:15:06Z", "comment": "/* 2008 Olympics attack on American nationals (2nd nomination) */", "size": 0, "sizediff": -3759}, {"userid": 7625701, "user": "Crashingthewaves", "pageid": 18798272, "revid": 231686963, "parentid": 231685586, "ns": 3, "title": "User talk:Crashingthewaves", "timestamp": "2008-08-13T14:24:24Z", "comment": "/* 2008 Olympics attack on American nationals (2nd nomination) */", "size": 0, "sizediff": -3908}, {"userid": 7625701, "user": "Crashingthewaves", "pageid": 18798272, "revid": 231688594, "parentid": 231688049, "ns": 3, "title": "User talk:Crashingthewaves", "timestamp": "2008-08-13T14:34:08Z", "comment": "[[WP:AES|\u2190]] Blanked the page", "size": 0, "sizediff": -4147}]